sunraster/__init__.py
sunraster/_version.py
sunraster/meta.py
sunraster/spectrogram.py
sunraster/spectrogram_sequence.py
sunraster/version.py
sunraster/data/README.rst
sunraster/instr/__init__.py
sunraster/instr/spice.py
sunraster/instr/tests/__init__.py
sunraster/instr/tests/test_spice.py
sunraster/tests/__init__.py
sunraster/tests/test_spectrogram.py
sunraster/tests/test_spectrogramsequence.py
sunraster/tests/data/solo_L2_spice-n-ras-db_20200602T081733_V01_12583760-000.fits
sunraster/tests/data/solo_L2_spice-n-sit_20200620T235901_V01_16777431-000.fits
sunraster-0.7.0.dist-info/licenses/LICENSE.rst
sunraster-0.7.0.dist-info/METADATA
sunraster-0.7.0.dist-info/WHEEL
sunraster-0.7.0.dist-info/top_level.txt
sunraster-0.7.0.dist-info/RECORD
