Metadata-Version: 2.4
Name: sunraster
Version: 0.7.0
Summary: sunraster is an open-source Python library that provides the tools to read in and analyze spectrogram data.
Author-email: The SunPy Community <sunpy@googlegroups.com>
License: Copyright (c) 2024, The SunPy Community
Project-URL: Homepage, https://sunpy.org
Project-URL: Source Code, https://github.com/sunpy/sunraster
Project-URL: Download, https://pypi.org/project/sunraster
Project-URL: Documentation, https://docs.sunpy.org/projects/sunraster
Project-URL: Changelog, https://docs.sunpy.org/projects/sunraster/en/stable/whatsnew/changelog.html
Project-URL: Issue Tracker, https://github.com/sunpy/sunraster/issues
Requires-Python: >=3.12
License-File: LICENSE.rst
Requires-Dist: numpy>=1.26.0
Requires-Dist: astropy>=6.1.0
Requires-Dist: ndcube[all]>=2.3.2
Provides-Extra: all
Requires-Dist: sunraster[instr]; extra == "all"
Provides-Extra: instr
Requires-Dist: sunpy>=7.0; extra == "instr"
Provides-Extra: tests
Requires-Dist: pytest; extra == "tests"
Requires-Dist: pytest-doctestplus; extra == "tests"
Requires-Dist: pytest-cov; extra == "tests"
Requires-Dist: pytest-astropy; extra == "tests"
Requires-Dist: pytest-xdist; extra == "tests"
Provides-Extra: docs
Requires-Dist: sphinx; extra == "docs"
Requires-Dist: sphinx-automodapi; extra == "docs"
Requires-Dist: sphinx-changelog; extra == "docs"
Requires-Dist: sunpy-sphinx-theme; extra == "docs"
Requires-Dist: packaging; extra == "docs"
Requires-Dist: sphinx-changelog; extra == "docs"
Requires-Dist: sphinx-gallery; extra == "docs"
Dynamic: license-file
